dsh/__init__.py
dsh/ans.py
dsh/api.py
dsh/evaluators.py
dsh/executors.py
dsh/main.py
dsh/matchers.py
dsh/node.py
dsh/shell.py
dsh/test.py
dsh/data/schema.yml
dsh2-2.0.4.dist-info/METADATA
dsh2-2.0.4.dist-info/RECORD
dsh2-2.0.4.dist-info/WHEEL
dsh2-2.0.4.dist-info/entry_points.txt
dsh2-2.0.4.dist-info/top_level.txt
