Metadata-Version: 2.1
Name: dsh2
Version: 2.0.4
Summary: console application to organize commands and environments
Home-page: https://github.com/flashashen/dsh2
Author: flashashen
Author-email: flashashen@gmail.com
License: MIT
Keywords: shell console yaml
Platform: osx
Platform: linux
Classifier: License :: OSI Approved :: MIT License
Classifier: Programming Language :: Python :: 2.7
Classifier: Programming Language :: Python :: 3.6
Classifier: Topic :: Software Development
Classifier: Environment :: Console
Classifier: Operating System :: MacOS
Classifier: Operating System :: POSIX :: Linux
Classifier: Development Status :: 3 - Alpha
Requires-Dist: flange
Requires-Dist: prompt-toolkit (!=1.5.1,<2.0,>1.0)
Requires-Dist: six
